pydispix/__init__.py
pydispix/autodraw.py
pydispix/canvas.py
pydispix/church.py
pydispix/churches.py
pydispix/client.py
pydispix/color.py
pydispix/errors.py
pydispix/log.py
pydispix/multiplexing.py
pydispix/ratelimits.py
pydispix/utils.py
pydispix-1.2.1.dist-info/LICENSE.txt
pydispix-1.2.1.dist-info/WHEEL
pydispix-1.2.1.dist-info/METADATA
pydispix-1.2.1.dist-info/RECORD
