Metadata-Version: 2.1
Name: pydispix
Version: 1.2.1
Summary: API wrapper for python-discord's pixels.
Home-page: https://github.com/ItsDrike/pydispix
License: MIT
Author: ItsDrike
Author-email: itsdrikeofficial@gmail.com
Requires-Python: >=3.8.0,<3.9.0
Classifier: Intended Audience :: Developers
Classifier: License :: OSI Approved :: MIT License
Classifier: Operating System :: OS Independent
Classifier: Programming Language :: Python :: 3
Classifier: Programming Language :: Python :: 3.8
Classifier: Programming Language :: Python :: 3.9
Requires-Dist: colorama (>=0.4.4,<0.5.0)
Requires-Dist: matplotlib (>=3.4.2,<3.5.0)
Requires-Dist: pillow (>=8.2.0,<8.3.0)
Requires-Dist: requests (>=2.25.1,<2.26.0)
Project-URL: Repository, https://github.com/ItsDrike/pydispix
